iacob/__init__.py
iacob/resources/Style_Application.qss
iacob/resources/help_pdf.pdf
iacob/resources/images/all.png
iacob/resources/images/arrowdown.png
iacob/resources/images/arrowup.png
iacob/resources/images/chat_pixel.jpg
iacob/resources/images/close.png
iacob/resources/images/csv.png
iacob/resources/images/ddd.png
iacob/resources/images/down-arrow.png
iacob/resources/images/error.png
iacob/resources/images/folder.png
iacob/resources/images/image.png
iacob/resources/images/logo.jpg
iacob/resources/images/plus.png
iacob/resources/images/up-arrow.png
iacob/resources/images/warning.png
iacob/src/IACOB.py
iacob/src/__init__.py
iacob/src/globals.py
iacob/src/Controller/ImportFile_Controller.py
iacob/src/Controller/LoadingPopup.py
iacob/src/Controller/MainWindow_Controller.py
iacob/src/Controller/ThreadClasses.py
iacob/src/Controller/__init__.py
iacob/src/Model/ExportPreviousFiles.py
iacob/src/Model/ImportConfig_Files.py
iacob/src/Model/ImportData_Files.py
iacob/src/Model/ImportFilters_Files.py
iacob/src/Model/ImportFlut_Files.py
iacob/src/Model/ImportName_Files.py
iacob/src/Model/ImportPreviousFiles.py
iacob/src/Model/ImportProject_Files.py
iacob/src/Model/__init__.py
iacob/src/Model/Data_Storage/ConnGraphSave_Model.py
iacob/src/Model/Data_Storage/ConnGraph_Model.py
iacob/src/Model/Data_Storage/DataSingleton_Model.py
iacob/src/Model/Data_Storage/FiltersSave_Model.py
iacob/src/Model/Data_Storage/Filters_Model.py
iacob/src/Model/Data_Storage/Project_Model.py
iacob/src/Model/Data_Storage/__init__.py
iacob/src/View/ImportFile_View.py
iacob/src/View/MainWindow_View.py
iacob/src/View/__init__.py
iacob/src/View/CustomWidgets/CenteredWidget_Widget.py
iacob/src/View/CustomWidgets/CheckGridLabel_Widget.py
iacob/src/View/CustomWidgets/ConnGraphic_Widget.py
iacob/src/View/CustomWidgets/FlowLayout_Layout.py
iacob/src/View/CustomWidgets/GTGraphic_Widget.py
iacob/src/View/CustomWidgets/Graphic_Widget.py
iacob/src/View/CustomWidgets/TableWidgetItemCustom_Widget.py
iacob-1.0.7.dist-info/METADATA
iacob-1.0.7.dist-info/WHEEL
iacob-1.0.7.dist-info/entry_points.txt
iacob-1.0.7.dist-info/top_level.txt
iacob-1.0.7.dist-info/RECORD
