Metadata-Version: 2.1
Name: iacob
Version: 1.0.7
Summary: Development of an interactive brain connectivity data mining tool
Home-page: https://scm.univ-tours.fr/projetspublics/lifat/iacob
Author: Thibaud SCRIBE, Enzo CREUZET
Author-email: thibaud.scribe@etu.univ-tours.fr, enzo.creuzet@etu.univ-tours.fr
Requires-Python: >=3.10, <3.13
Requires-Dist: PyQt5 <=5.15.10,>=5.15.0
Requires-Dist: matplotlib <=3.9.1,>=3.5.0
Requires-Dist: networkx <=3.3.0,>=3.0
Requires-Dist: scipy <=1.14.0,>=1.8.0
Requires-Dist: pyqtgraph <=0.13.7,>=0.11.0
